vibetools/__init__.py
vibetools/_internal/__init__.py
vibetools/_internal/logger.py
vibetools/_internal/vibe_config.py
vibetools/_internal/vibe_llm_client.py
vibetools/_internal/vibe_mode.py
vibetools/exceptions/__init__.py
vibetools/exceptions/exceptions.py
vibetools/llms/gemini_wrapper.py
vibetools/llms/openai_wrapper.py
vibetools/llms/vibe_base_llm.py
vibetools-1.0.4.dist-info/METADATA
vibetools-1.0.4.dist-info/WHEEL
vibetools-1.0.4.dist-info/licenses/LICENSE
vibetools-1.0.4.dist-info/RECORD
