Metadata-Version: 2.4
Name: vibetools
Version: 1.0.4
Summary: Core modules shared across vibe-engineers libraries.
Project-URL: Homepage, https://github.com/vibe-engineers/vibetools
Project-URL: Issues, https://github.com/vibe-engineers/vibetools/issues
Author-email: vibe-engineers <vibe.engineers.team@gmail.com>, tjtanjin <cjtanjin@gmail.com>, konglyyy <kongleyi99@gmail.com>
License-File: LICENSE
Classifier: License :: OSI Approved :: MIT License
Classifier: Operating System :: OS Independent
Classifier: Programming Language :: Python :: 3
Requires-Python: >=3.0
